odoo/addons/ssi_accounting_entry_mixin/README.rst
odoo/addons/ssi_accounting_entry_mixin/__init__.py
odoo/addons/ssi_accounting_entry_mixin/__manifest__.py
odoo/addons/ssi_accounting_entry_mixin/i18n/ssi_accounting_entry_mixin.pot
odoo/addons/ssi_accounting_entry_mixin/models/__init__.py
odoo/addons/ssi_accounting_entry_mixin/models/mixin_account_move.py
odoo/addons/ssi_accounting_entry_mixin/models/mixin_account_move_double_line.py
odoo/addons/ssi_accounting_entry_mixin/models/mixin_account_move_single_line.py
odoo/addons/ssi_accounting_entry_mixin/models/mixin_tax_line.py
odoo/addons/ssi_accounting_entry_mixin/static/description/icon.png
odoo14_addon_ssi_accounting_entry_mixin-14.0.1.10.0.dist-info/METADATA
odoo14_addon_ssi_accounting_entry_mixin-14.0.1.10.0.dist-info/WHEEL
odoo14_addon_ssi_accounting_entry_mixin-14.0.1.10.0.dist-info/top_level.txt
odoo14_addon_ssi_accounting_entry_mixin-14.0.1.10.0.dist-info/RECORD
